{
    "wallpaper": "/home/jason/.config/wpg/wallpapers/1406561-m.jpg",
    "alpha": "100",

    "special": {
        "background": "#040309",
        "foreground": "#ffffd5",
        "cursor": "#ffffd5"
    },
    "colors": {
        "color0": "#040309",
        "color1": "#695665",
        "color2": "#9d9ab4",
        "color3": "#946568",
        "color4": "#812439",
        "color5": "#5c4b40",
        "color6": "#beaa92",
        "color7": "#f1d3ac",
        "color8": "#160f2e",
        "color9": "#95628b",
        "color10": "#bbb3ff",
        "color11": "#d07378",
        "color12": "#b22445",
        "color13": "#825e48",
        "color14": "#ffe0a8",
        "color15": "#ffffd5"
    }
}
